papyrus_structure_pipeline/__init__.py
papyrus_structure_pipeline/standardizer.py
papyrus_structure_pipeline-0.0.5.dist-info/LICENSE
papyrus_structure_pipeline-0.0.5.dist-info/METADATA
papyrus_structure_pipeline-0.0.5.dist-info/WHEEL
papyrus_structure_pipeline-0.0.5.dist-info/top_level.txt
papyrus_structure_pipeline-0.0.5.dist-info/RECORD
